jsonpathgenerator.py
jsonpathgenerator-0.0.2.dist-info/LICENSE
jsonpathgenerator-0.0.2.dist-info/METADATA
jsonpathgenerator-0.0.2.dist-info/WHEEL
jsonpathgenerator-0.0.2.dist-info/top_level.txt
jsonpathgenerator-0.0.2.dist-info/RECORD
