Metadata-Version: 2.1
Name: jsonpathgenerator
Version: 0.0.2
Summary: Get Json path from a nested json document. specify notation dot or bracket
Home-page: https://github.com/uniquetech/JSONPathGenerator.git
Author: hariharan sivakumar
Author-email: catchhster@gmail.com
License: UNKNOWN
Keywords: Json Jsonpath xpath jsonnotation json parser safe parser
Platform: UNKNOWN
Classifier: Development Status :: 3 - Alpha
Classifier: Intended Audience :: Developers
Classifier: Topic :: Software Development :: Build Tools
Classifier: License :: OSI Approved :: MIT License
Classifier: Programming Language :: Python :: 3
Classifier: Programming Language :: Python :: 3.5
Classifier: Programming Language :: Python :: 3.6
Classifier: Programming Language :: Python :: 3.7
Classifier: Programming Language :: Python :: 3.8
Classifier: Programming Language :: Python :: 3 :: Only
Requires-Python: >=3.5, <4
